holisticai_sdk/__about__.py
holisticai_sdk/__init__.py
holisticai_sdk/session.py
holisticai_sdk/assessments/__assessments.py
holisticai_sdk/assessments/__init__.py
holisticai_sdk/assessments/core.py
holisticai_sdk/assessments/environment.py
holisticai_sdk/assessments/model_context.py
holisticai_sdk/assessments/requirements.txt
holisticai_sdk/assessments/run_assessment.py
holisticai_sdk/engine/__about__.py
holisticai_sdk/engine/__init__.py
holisticai_sdk/engine/bootstrap.py
holisticai_sdk/engine/assessment/__init__.py
holisticai_sdk/engine/assessment/core.py
holisticai_sdk/engine/definitions/__init__.py
holisticai_sdk/engine/definitions/_base.py
holisticai_sdk/engine/definitions/_bootstrap.py
holisticai_sdk/engine/definitions/_dataset_obj.py
holisticai_sdk/engine/definitions/_dataset_obj.pyi
holisticai_sdk/engine/definitions/_datasets.py
holisticai_sdk/engine/definitions/_metric_entries.py
holisticai_sdk/engine/definitions/_metric_params.py
holisticai_sdk/engine/definitions/_optimizer.py
holisticai_sdk/engine/definitions/_vertical_settings.py
holisticai_sdk/engine/definitions/_vertical_settings_obj.py
holisticai_sdk/engine/definitions/_vertical_settings_obj.pyi
holisticai_sdk/engine/definitions/metric_entry_obj.py
holisticai_sdk/engine/definitions/metric_entry_obj.pyi
holisticai_sdk/engine/metrics/__init__.py
holisticai_sdk/engine/metrics/utils.py
holisticai_sdk/engine/metrics/bias/__init__.py
holisticai_sdk/engine/metrics/bias/_compute_cost.py
holisticai_sdk/engine/metrics/bias/_compute_metrics.py
holisticai_sdk/engine/metrics/bias/_compute_metrics.pyi
holisticai_sdk/engine/metrics/bias/_learning_metrics.py
holisticai_sdk/engine/metrics/bias/_metric_entry.py
holisticai_sdk/engine/metrics/efficacy/__init__.py
holisticai_sdk/engine/metrics/efficacy/_compute_cost.py
holisticai_sdk/engine/metrics/efficacy/_compute_metrics.py
holisticai_sdk/engine/metrics/efficacy/_compute_metrics.pyi
holisticai_sdk/engine/metrics/efficacy/_learning_metrics.py
holisticai_sdk-0.0.24.dist-info/METADATA
holisticai_sdk-0.0.24.dist-info/WHEEL
holisticai_sdk-0.0.24.dist-info/licenses/LICENSE.txt
holisticai_sdk-0.0.24.dist-info/RECORD
