Metadata-Version: 2.4
Name: holisticai-sdk
Version: 0.0.24
Project-URL: Documentation, https://github.com/cristian/haisdk#readme
Project-URL: Issues, https://github.com/cristian/haisdk/issues
Project-URL: Source, https://github.com/cristian/haisdk
Author-email: cristian <cristian.munoz@holisticai.com>
License-Expression: MIT
License-File: LICENSE.txt
Classifier: Development Status :: 4 - Beta
Classifier: Programming Language :: Python
Classifier: Programming Language :: Python :: 3.9
Classifier: Programming Language :: Python :: 3.10
Classifier: Programming Language :: Python :: 3.11
Classifier: Programming Language :: Python :: 3.12
Classifier: Programming Language :: Python :: Implementation :: CPython
Classifier: Programming Language :: Python :: Implementation :: PyPy
Requires-Python: >=3.9
Requires-Dist: requests
Requires-Dist: urllib3
Provides-Extra: full
Requires-Dist: holisticai[bias]>=1.0.14; extra == 'full'
Requires-Dist: pydantic; extra == 'full'
Requires-Dist: requests; extra == 'full'
